charlette/__init__.py
charlette/__main__.py
charlette/__version__.py
charlette/apps.py
charlette/cli.py
charlette/endpoints.py
charlette/utils.py
charlette/app_template/__init__.py
charlette/app_template/endpoints.py
charlette/app_template/models.py
charlette-0.0.2.dist-info/METADATA
charlette-0.0.2.dist-info/RECORD
charlette-0.0.2.dist-info/WHEEL
charlette-0.0.2.dist-info/entry_points.txt
charlette-0.0.2.dist-info/top_level.txt
