Metadata-Version: 2.1
Name: charlette
Version: 0.0.2
Summary: Django app that uses Starlette components with Channels.
Home-page: https://github.com/erm/charlette
Author: Jordan Eremieff
Author-email: jordan@eremieff.com
License: MIT License
Platform: UNKNOWN
Requires-Dist: Django
Requires-Dist: channels
Requires-Dist: starlette
Requires-Dist: innate (==0.1.1)
